setup.py
nagplug/__init__.py
nagplug.egg-info/PKG-INFO
nagplug.egg-info/SOURCES.txt
nagplug.egg-info/dependency_links.txt
nagplug.egg-info/top_level.txt