Metadata-Version: 1.1
Name: nagplug
Version: 1.1
Summary: Nagios guidelines-compliant monitoring plugin creation library (Shinken, Icinga, Centreon)
Home-page: https://github.com/nlm/nagplug
Author: Nicolas Limage
Author-email: UNKNOWN
License: MIT
Keywords: nagios plugin shinken icinga centreon monitoring
Platform: UNKNOWN
Classifier: Development Status :: 5 - Production/Stable
Classifier: Environment :: Console
Classifier: Intended Audience :: Developers
Classifier: License :: OSI Approved :: MIT License
Classifier: Operating System :: OS Independent
Classifier: Programming Language :: Python
Classifier: Topic :: System :: Monitoring
